{
    "$schema": "http://json-schema.org/draft-07/schema",
    "$id": "http://example.com/example.json",
    "type": "object",
    "title": "The root schema",
    "description": "The root schema comprises the entire JSON document.",
    "default": {},
    "examples": [
        {
            "username": "test@test.com",
            "password": "Test",
            "fistName": "afas",
            "lastName": "fasfds"
        }
    ],
    "required": [
        "username",
        "password"       
    ],
    "properties": {
        "username": {
            "$id": "#/properties/username",
            "type": "string",
            "title": "The username schema",
            "description": "An explanation about the purpose of this instance.",
            "default": "",
            "examples": [
                "test@test.com"
            ]
        },
        "password": {
            "$id": "#/properties/password",
            "type": "string",
            "title": "The password schema",
            "description": "An explanation about the purpose of this instance.",
            "default": "",
            "examples": [
                "Test"
            ]
        },
        "fistName": {
            "$id": "#/properties/fistName",
            "type": "string",
            "title": "The fistName schema",
            "description": "An explanation about the purpose of this instance.",
            "default": "",
            "examples": [
                "afas"
            ]
        },
        "lastName": {
            "$id": "#/properties/lastName",
            "type": "string",
            "title": "The lastName schema",
            "description": "An explanation about the purpose of this instance.",
            "default": "",
            "examples": [
                "fasfds"
            ]
        }
    },
    "additionalProperties": true
}